{
    "ActorList": {
        "0": {
            "ActorProperties": {
                "Name": "MainGround",
                "ID": 1,
                "ActorGroup": "GROUND",
                "state": "active",
                "Transform": {
                    "WorldPosition": {
                        "x": -482.0,
                        "y": 0.0
                    },
                    "LocalPosition": {
                        "x": 0.0,
                        "y": 0.0
                    },
                    "Scale": {
                        "x": 1.0,
                        "y": 1.0
                    },
                    "Rotation": 0.0
                }
            },
            "ActorComponents": {
                "ComponentCount": 1,
                "0": {
                    "Name": "ColliderComponent",
                    "DrawOrder": 100,
                    "UpdateOrder": 100,
                    "OffsetPos": {
                        "x": 0.0,
                        "y": 0.0
                    },
                    "Scale": {
                        "x": 787.0,
                        "y": 101.0
                    }
                }
            }
        },
        "Count": 2,
        "1": {
            "ActorProperties": {
                "Name": "Player",
                "ID": 3,
                "ActorGroup": "PLAYER",
                "state": "active",
                "Transform": {
                    "WorldPosition": {
                        "x": -734.0,
                        "y": -188.0
                    },
                    "LocalPosition": {
                        "x": 0.0,
                        "y": 0.0
                    },
                    "Scale": {
                        "x": 1.0,
                        "y": 1.0
                    },
                    "Rotation": 0.0
                }
            },
            "ActorComponents": {
                "ComponentCount": 2,
                "0": {
                    "Name": "ColliderComponent",
                    "DrawOrder": 100,
                    "UpdateOrder": 100,
                    "OffsetPos": {
                        "x": 0.0,
                        "y": 0.0
                    },
                    "Scale": {
                        "x": 76.0,
                        "y": 130.0
                    }
                },
                "1": {
                    "Name": "Rigidbody2DComponent",
                    "DrawOrder": 100,
                    "UpdateOrder": 100,
                    "Mass": 1.0,
                    "FrictionCoeff": 0.10000000149011612,
                    "MaxVelocity": {
                        "x": 200.0,
                        "y": 600.0
                    }
                }
            }
        }
    },
    "ChunkData": {
        "ActorCount": 2,
        "Camera": {
            "TargetActor": 5,
            "RenderResolution": {
                "x": 1920.0,
                "y": 1080.0
            },
            "ScreenCenter": {
                "x": 960.0,
                "y": 540.0
            }
        }
    }
}
